README.md
setup.cfg
setup.py
tvmbase/__init__.py
tvmbase/batch_loader.py
tvmbase/client.py
tvmbase/constants.py
tvmbase/exceptions.py
tvmbase/types.py
tvmbase.egg-info/PKG-INFO
tvmbase.egg-info/SOURCES.txt
tvmbase.egg-info/dependency_links.txt
tvmbase.egg-info/not-zip-safe
tvmbase.egg-info/requires.txt
tvmbase.egg-info/top_level.txt
tvmbase/abi/__init__.py
tvmbase/abi/converter.py
tvmbase/models/__init__.py
tvmbase/models/boc_type.py
tvmbase/models/data.py
tvmbase/models/network.py
tvmbase/models/tvm/__init__.py
tvmbase/models/tvm/account.py
tvmbase/models/tvm/base.py
tvmbase/models/tvm/message.py
tvmbase/models/tvm/transaction.py
tvmbase/utils/__init__.py
tvmbase/utils/attrs_helper.py
tvmbase/utils/singleton.py
tvmbase/utils/to_ever.py
tvmbase/utils/tvm_utils.py