Metadata-Version: 2.1
Name: tvmbase
Version: 3.2.6
Summary: Part of Evertrace project | Base TVM models and utils
Home-page: https://github.com/abionics/tvmbase
Author: Alex Ermolaev
Author-email: abionics.dev@gmail.com
License: UNKNOWN
Keywords: evertrace tvm utils
Platform: UNKNOWN
Classifier: Intended Audience :: Developers
Classifier: Operating System :: OS Independent
Classifier: Programming Language :: Python :: 3
Classifier: Programming Language :: Python :: 3.9
Classifier: Programming Language :: Python :: 3.10
Classifier: Programming Language :: Python :: 3.11
Classifier: Topic :: Software Development :: Libraries :: Python Modules
